evidi_fabric/__init__.py
evidi_fabric/dag.py
evidi_fabric/dataverse.py
evidi_fabric/delta.py
evidi_fabric/fo.py
evidi_fabric/fs.py
evidi_fabric/items.py
evidi_fabric/notebook.py
evidi_fabric/powerbi.py
evidi_fabric/security.py
evidi_fabric/semanticmodel.py
evidi_fabric/spark.py
evidi_fabric/sql.py
evidi_fabric/test.py
evidi_fabric/utils.py
evidi_fabric-1.2.4.dist-info/LICENSE
evidi_fabric-1.2.4.dist-info/METADATA
evidi_fabric-1.2.4.dist-info/WHEEL
evidi_fabric-1.2.4.dist-info/RECORD
