Metadata-Version: 2.1
Name: evidi_fabric
Version: 1.2.4
Summary: 
Author: Uffe Friis Torlyn
Author-email: uffe.friis.torlyn@evidi.com
Requires-Python: >=3.10,<3.12
Classifier: Programming Language :: Python :: 3
Classifier: Programming Language :: Python :: 3.10
Classifier: Programming Language :: Python :: 3.11
